sampled/__init__.py
sampled/sampled.py
sampled-0.1.2.dist-info/DESCRIPTION.rst
sampled-0.1.2.dist-info/METADATA
sampled-0.1.2.dist-info/RECORD
sampled-0.1.2.dist-info/WHEEL
sampled-0.1.2.dist-info/metadata.json
sampled-0.1.2.dist-info/top_level.txt
