Metadata-Version: 2.0
Name: sampled
Version: 0.1.2
Summary: Decorator for reusable models in PyMC3
Home-page: https://github.com/ColCarroll/sampled
Author: Colin Carroll
Author-email: colcarroll@gmail.com
License: MIT
Platform: UNKNOWN
Classifier: Development Status :: 3 - Alpha
Classifier: Intended Audience :: Developers
Classifier: License :: OSI Approved :: MIT License
Classifier: Programming Language :: Python :: 3
Classifier: Programming Language :: Python :: 3.6
Requires-Dist: pymc3 (>=3.0)
